<?php

class JavaMnemonicEnum extends JavaEnum {

    const MNEMONIC_nop = 0x00;
    const MNEMONIC_aconst_null = 0x01;
    const MNEMONIC_iconst_m1 = 0x02;
    const MNEMONIC_iconst_0 = 0x03;
    const MNEMONIC_iconst_1 = 0x04;
    const MNEMONIC_iconst_2 = 0x05;
    const MNEMONIC_iconst_3 = 0x06;
    const MNEMONIC_iconst_4 = 0x07;
    const MNEMONIC_iconst_5 = 0x08;
    const MNEMONIC_lconst_0 = 0x09;
    const MNEMONIC_lconst_1 = 0x0A;
    const MNEMONIC_fconst_0 = 0x0B;
    const MNEMONIC_fconst_1 = 0x0C;
    const MNEMONIC_fconst_2 = 0x0D;
    const MNEMONIC_dconst_0 = 0x0E;
    const MNEMONIC_dconst_1 = 0x0F;
    const MNEMONIC_bipush = 0x10;
    const MNEMONIC_sipush = 0x11;
    const MNEMONIC_ldc = 0x12;
    const MNEMONIC_ldc_w = 0x13;
    const MNEMONIC_ldc2_w = 0x14;
    const MNEMONIC_iload = 0x15;
    const MNEMONIC_lload = 0x16;
    const MNEMONIC_fload = 0x17;
    const MNEMONIC_dload = 0x18;
    const MNEMONIC_aload = 0x19;
    const MNEMONIC_iload_0 = 0x1A;
    const MNEMONIC_iload_1 = 0x1B;
    const MNEMONIC_iload_2 = 0x1C;
    const MNEMONIC_iload_3 = 0x1D;
    const MNEMONIC_lload_0 = 0x1E;
    const MNEMONIC_lload_1 = 0x1F;
    const MNEMONIC_lload_2 = 0x20;
    const MNEMONIC_lload_3 = 0x21;
    const MNEMONIC_fload_0 = 0x22;
    const MNEMONIC_fload_1 = 0x23;
    const MNEMONIC_fload_2 = 0x24;
    const MNEMONIC_fload_3 = 0x25;
    const MNEMONIC_dload_0 = 0x26;
    const MNEMONIC_dload_1 = 0x27;
    const MNEMONIC_dload_2 = 0x28;
    const MNEMONIC_dload_3 = 0x29;
    const MNEMONIC_aload_0 = 0x2A;
    const MNEMONIC_aload_1 = 0x2B;
    const MNEMONIC_aload_2 = 0x2C;
    const MNEMONIC_aload_3 = 0x2D;
    const MNEMONIC_iaload = 0x2E;
    const MNEMONIC_laload = 0x2F;
    const MNEMONIC_faload = 0x30;
    const MNEMONIC_daload = 0x31;
    const MNEMONIC_aaload = 0x32;
    const MNEMONIC_baload = 0x33;
    const MNEMONIC_caload = 0x34;
    const MNEMONIC_saload = 0x35;
    const MNEMONIC_istore = 0x36;
    const MNEMONIC_lstore = 0x37;
    const MNEMONIC_fstore = 0x38;
    const MNEMONIC_dstore = 0x39;
    const MNEMONIC_astore = 0x3A;
    const MNEMONIC_istore_0 = 0x3B;
    const MNEMONIC_istore_1 = 0x3C;
    const MNEMONIC_istore_2 = 0x3D;
    const MNEMONIC_istore_3 = 0x3E;
    const MNEMONIC_lstore_0 = 0x3F;
    const MNEMONIC_lstore_1 = 0x40;
    const MNEMONIC_lstore_2 = 0x41;
    const MNEMONIC_lstore_3 = 0x42;
    const MNEMONIC_fstore_0 = 0x43;
    const MNEMONIC_fstore_1 = 0x44;
    const MNEMONIC_fstore_2 = 0x45;
    const MNEMONIC_fstore_3 = 0x46;
    const MNEMONIC_dstore_0 = 0x47;
    const MNEMONIC_dstore_1 = 0x48;
    const MNEMONIC_dstore_2 = 0x49;
    const MNEMONIC_dstore_3 = 0x4A;
    const MNEMONIC_astore_0 = 0x4B;
    const MNEMONIC_astore_1 = 0x4C;
    const MNEMONIC_astore_2 = 0x4D;
    const MNEMONIC_astore_3 = 0x4E;
    const MNEMONIC_iastore = 0x4F;
    const MNEMONIC_lastore = 0x50;
    const MNEMONIC_fastore = 0x51;
    const MNEMONIC_dastore = 0x52;
    const MNEMONIC_aastore = 0x53;
    const MNEMONIC_bastore = 0x54;
    const MNEMONIC_castore = 0x55;
    const MNEMONIC_sastore = 0x56;
    const MNEMONIC_pop = 0x57;
    const MNEMONIC_pop2 = 0x58;
    const MNEMONIC_dup = 0x59;
    const MNEMONIC_dup_x1 = 0x5A;
    const MNEMONIC_dup_x2 = 0x5B;
    const MNEMONIC_dup2 = 0x5C;
    const MNEMONIC_dup2_x1 = 0x5D;
    const MNEMONIC_dup2_x2 = 0x5E;
    const MNEMONIC_swap = 0x5F;
    const MNEMONIC_iadd = 0x60;
    const MNEMONIC_ladd = 0x61;
    const MNEMONIC_fadd = 0x62;
    const MNEMONIC_dadd = 0x63;
    const MNEMONIC_isub = 0x64;
    const MNEMONIC_lsub = 0x65;
    const MNEMONIC_fsub = 0x66;
    const MNEMONIC_dsub = 0x67;
    const MNEMONIC_imul = 0x68;
    const MNEMONIC_lmul = 0x69;
    const MNEMONIC_fmul = 0x6A;
    const MNEMONIC_dmul = 0x6B;
    const MNEMONIC_idiv = 0x6C;
    const MNEMONIC_ldiv = 0x6D;
    const MNEMONIC_fdiv = 0x6E;
    const MNEMONIC_ddiv = 0x6F;
    const MNEMONIC_irem = 0x70;
    const MNEMONIC_lrem = 0x71;
    const MNEMONIC_frem = 0x72;
    const MNEMONIC_drem = 0x73;
    const MNEMONIC_ineg = 0x74;
    const MNEMONIC_lneg = 0x75;
    const MNEMONIC_fneg = 0x76;
    const MNEMONIC_dneg = 0x77;
    const MNEMONIC_ishl = 0x78;
    const MNEMONIC_lshl = 0x79;
    const MNEMONIC_ishr = 0x7A;
    const MNEMONIC_lshr = 0x7B;
    const MNEMONIC_iushr = 0x7C;
    const MNEMONIC_lushr = 0x7D;
    const MNEMONIC_iand = 0x7E;
    const MNEMONIC_land = 0x7F;
    const MNEMONIC_ior = 0x80;
    const MNEMONIC_lor = 0x81;
    const MNEMONIC_ixor = 0x82;
    const MNEMONIC_lxor = 0x83;
    const MNEMONIC_iinc = 0x84;
    const MNEMONIC_i2l = 0x85;
    const MNEMONIC_i2f = 0x86;
    const MNEMONIC_i2d = 0x87;
    const MNEMONIC_l2i = 0x88;
    const MNEMONIC_l2f = 0x89;
    const MNEMONIC_l2d = 0x8A;
    const MNEMONIC_f2i = 0x8B;
    const MNEMONIC_f2l = 0x8C;
    const MNEMONIC_f2d = 0x8D;
    const MNEMONIC_d2i = 0x8E;
    const MNEMONIC_d2l = 0x8F;
    const MNEMONIC_d2f = 0x90;
    const MNEMONIC_i2b = 0x91;
    const MNEMONIC_i2c = 0x92;
    const MNEMONIC_i2s = 0x93;
    const MNEMONIC_lcmp = 0x94;
    const MNEMONIC_fcmpl = 0x95;
    const MNEMONIC_fcmpg = 0x96;
    const MNEMONIC_dcmpl = 0x97;
    const MNEMONIC_dcmpg = 0x98;
    const MNEMONIC_ifeq = 0x99;
    const MNEMONIC_ifne = 0x9A;
    const MNEMONIC_iflt = 0x9B;
    const MNEMONIC_ifge = 0x9C;
    const MNEMONIC_ifgt = 0x9D;
    const MNEMONIC_ifle = 0x9E;
    const MNEMONIC_if_icmpeq = 0x9F;
    const MNEMONIC_if_icmpne = 0xA0;
    const MNEMONIC_if_icmplt = 0xA1;
    const MNEMONIC_if_icmpge = 0xA2;
    const MNEMONIC_if_icmpgt = 0xA3;
    const MNEMONIC_if_icmple = 0xA4;
    const MNEMONIC_if_acmpeq = 0xA5;
    const MNEMONIC_if_acmpne = 0xA6;
    const MNEMONIC_goto = 0xA7;
    const MNEMONIC_jsr = 0xA8;
    const MNEMONIC_ret = 0xA9;
    const MNEMONIC_tableswitch = 0xAA;
    const MNEMONIC_lookupswitch = 0xAB;
    const MNEMONIC_ireturn = 0xAC;
    const MNEMONIC_lreturn = 0xAD;
    const MNEMONIC_freturn = 0xAE;
    const MNEMONIC_dreturn = 0xAF;
    const MNEMONIC_areturn = 0xB0;
    const MNEMONIC_return = 0xB1;
    const MNEMONIC_getstatic = 0xB2;
    const MNEMONIC_putstatic = 0xB3;
    const MNEMONIC_getfield = 0xB4;
    const MNEMONIC_putfield = 0xB5;
    const MNEMONIC_invokevirtual = 0xB6;
    const MNEMONIC_invokespecial = 0xB7;
    const MNEMONIC_invokestatic = 0xB8;
    const MNEMONIC_invokeinterface = 0xB9;
    const MNEMONIC_invokedynamic = 0xBA;
    const MNEMONIC_new = 0xBB;
    const MNEMONIC_newarray = 0xBC;
    const MNEMONIC_anewarray = 0xBD;
    const MNEMONIC_arraylength = 0xBE;
    const MNEMONIC_athrow = 0xBF;
    const MNEMONIC_checkcast = 0xC0;
    const MNEMONIC_instanceof = 0xC1;
    const MNEMONIC_monitorenter = 0xC2;
    const MNEMONIC_monitorexit = 0xC3;
    const MNEMONIC_wide = 0xC4;
    const MNEMONIC_multianewarray = 0xC5;
    const MNEMONIC_ifnull = 0xC6;
    const MNEMONIC_ifnonnull = 0xC7;
    const MNEMONIC_goto_w = 0xC8;
    const MNEMONIC_jsr_w = 0xC9;
    const MNEMONIC_breakpoint = 0xCA;
    const MNEMONIC_impdep1 = 0xFE;
    const MNEMONIC_impdep2 = 0xFF;
    

}